{"name": "125341262", "result": [{"taxonid": 125341262, "scientific_name": "Pseudoxiphophorus cataractae", "kingdom": "ANIMALIA", "phylum": "CHORDATA", "class": "ACTINOPTERYGII", "order": "CYPRINODONTIFORMES", "family": "POECILIIDAE", "genus": "Pseudoxiphophorus", "main_common_name": "Bute", "authority": "(Rosen, 1979)", "published_year": 2020, "assessment_date": "2019-10-14", "category": "VU", "criteria": "D2", "population_trend": "Unknown", "marine_system": false, "freshwater_system": true, "terrestrial_system": false, "assessor": "McMahan, C., Quintana, Y, & Lyons, T.J.", "reviewer": "Fuentes, C. & Elias, D.J.", "aoo_km2": "4", "eoo_km2": "4", "elevation_upper": null, "elevation_lower": null, "depth_upper": null, "depth_lower": null, "errata_flag": null, "errata_reason": null, "amended_flag": null, "amended_reason": null}]}