{"id": "118042765", "result": [{"code": "2.3", "title": "Livestock farming & ranching", "timing": "Ongoing", "scope": "Minority (<50%)", "severity": "Causing/Could cause fluctuations", "score": "Low Impact: 5", "invasive": null}, {"code": "2.3.2", "title": "Small-holder grazing, ranching or farming", "timing": "Ongoing", "scope": "Minority (<50%)", "severity": "Causing/Could cause fluctuations", "score": "Low Impact: 5", "invasive": null}, {"code": "3.2", "title": "Mining & quarrying", "timing": "Ongoing", "scope": "Minority (<50%)", "severity": "Unknown", "score": "Unknown", "invasive": null}, {"code": "5.3", "title": "Logging & wood harvesting", "timing": "Ongoing", "scope": "Minority (<50%)", "severity": "Unknown", "score": "Unknown", "invasive": null}, {"code": "5.3.3", "title": "Unintentional effects: (subsistence/small scale) [harvest]", "timing": "Ongoing", "scope": "Minority (<50%)", "severity": "Unknown", "score": "Unknown", "invasive": null}, {"code": "7.1", "title": "Fire & fire suppression", "timing": "Ongoing", "scope": "Minority (<50%)", "severity": "Unknown", "score": "Unknown", "invasive": null}, {"code": "7.1.1", "title": "Increase in fire frequency/intensity", "timing": "Ongoing", "scope": "Minority (<50%)", "severity": "Unknown", "score": "Unknown", "invasive": null}]}