{"name": "20972", "result": [{"taxonid": 20972, "scientific_name": "Stygionympha dicksoni", "kingdom": "ANIMALIA", "phylum": "ARTHROPODA", "class": "INSECTA", "order": "LEPIDOPTERA", "family": "NYMPHALIDAE", "genus": "Stygionympha", "main_common_name": "Dickson's Hillside Brown", "authority": "(Riley, 1938)", "published_year": 2020, "assessment_date": "2018-02-20", "category": "CR", "criteria": "B1ab(iii)+2ab(iii)", "population_trend": "Unknown", "marine_system": false, "freshwater_system": false, "terrestrial_system": true, "assessor": "Ball, J.B.", "reviewer": "Kirkman, S., Raimondo, D., Oberprieler, R.G. & B\u00f6hm, M.", "aoo_km2": "0-20", "eoo_km2": "0-57", "elevation_upper": null, "elevation_lower": null, "depth_upper": null, "depth_lower": null, "errata_flag": null, "errata_reason": null, "amended_flag": null, "amended_reason": null}]}