{"name": "56092080", "result": [{"taxonid": 56092080, "scientific_name": "Puntius madhusoodani", "kingdom": "ANIMALIA", "phylum": "CHORDATA", "class": "ACTINOPTERYGII", "order": "CYPRINIFORMES", "family": "CYPRINIDAE", "genus": "Puntius", "main_common_name": null, "authority": "Kumar, Benno Pereira &amp; Radhakrishnan, 2012", "published_year": 2023, "assessment_date": "2021-03-28", "category": "CR", "criteria": "B1ab(iii)", "population_trend": "Unknown", "marine_system": false, "freshwater_system": true, "terrestrial_system": false, "assessor": "Dahanukar, N.", "reviewer": "Raghavan, R.", "aoo_km2": "36", "eoo_km2": "36", "elevation_upper": 4, "elevation_lower": 4, "depth_upper": null, "depth_lower": null, "errata_flag": null, "errata_reason": null, "amended_flag": null, "amended_reason": null}]}