{"name": "1167", "result": [{"taxonid": 1167, "scientific_name": "Amphidromus cognatus", "kingdom": "ANIMALIA", "phylum": "MOLLUSCA", "class": "GASTROPODA", "order": "STYLOMMATOPHORA", "family": "CAMAENIDAE", "genus": "Amphidromus", "main_common_name": null, "authority": "Fulton, 1907", "published_year": 2020, "assessment_date": "2015-03-05", "category": "EN", "criteria": "B1ab(iii)+2ab(iii)", "population_trend": "Decreasing", "marine_system": false, "freshwater_system": false, "terrestrial_system": true, "assessor": "Kessner, V., K\u00f6hler, F., Ponder, W. & Seddon, M.B.", "reviewer": "Stanisic, J. & Neubert, E.", "aoo_km2": "12-500", "eoo_km2": "12-5000", "elevation_upper": null, "elevation_lower": null, "depth_upper": null, "depth_lower": null, "errata_flag": null, "errata_reason": null, "amended_flag": null, "amended_reason": null}]}