{"name": "128725353", "result": [{"taxonid": 128725353, "scientific_name": "Schistura macrolepis", "kingdom": "ANIMALIA", "phylum": "CHORDATA", "class": "ACTINOPTERYGII", "order": "CYPRINIFORMES", "family": "NEMACHEILIDAE", "genus": "Schistura", "main_common_name": null, "authority": "Mirza &amp; B\u0103n\u0103rescu, 1981", "published_year": 2021, "assessment_date": "2020-02-27", "category": "EN", "criteria": "A2c+3c", "population_trend": "Decreasing", "marine_system": false, "freshwater_system": true, "terrestrial_system": false, "assessor": "Rafique, M., Zafarullah, M., Daniels, A., Qureshi, I., Imran, M. & Johnson, J.A.", "reviewer": "Molur, S. & Ali, A.", "aoo_km2": "1568", "eoo_km2": "17415", "elevation_upper": 950, "elevation_lower": 150, "depth_upper": null, "depth_lower": null, "errata_flag": null, "errata_reason": null, "amended_flag": null, "amended_reason": null}]}