{"id": "176402183", "result": [{"code": "7.2", "title": "Dams & water management/use", "timing": "Ongoing", "scope": "Unknown", "severity": "Unknown", "score": "Unknown", "invasive": null}, {"code": "7.2.10", "title": "Large dams", "timing": "Ongoing", "scope": "Unknown", "severity": "Unknown", "score": "Unknown", "invasive": null}, {"code": "7.3", "title": "Other ecosystem modifications", "timing": "Ongoing", "scope": "Majority (50-90%)", "severity": "Rapid Declines", "score": "Medium Impact: 7", "invasive": null}, {"code": "9.3", "title": "Agricultural & forestry effluents", "timing": "Ongoing", "scope": null, "severity": null, "score": "Low Impact: 3", "invasive": null}, {"code": "9.3.2", "title": "Soil erosion, sedimentation", "timing": "Ongoing", "scope": null, "severity": null, "score": "Low Impact: 3", "invasive": null}]}