{"name": "177896807", "result": [{"taxonid": 177896807, "scientific_name": "Drepanosticta schorri", "kingdom": "ANIMALIA", "phylum": "ARTHROPODA", "class": "INSECTA", "order": "ODONATA", "family": "PLATYSTICTIDAE", "genus": "Drepanosticta", "main_common_name": null, "authority": "Villanueva, 2011", "published_year": 2021, "assessment_date": "2020-06-28", "category": "CR", "criteria": "B1ab(ii,iii)", "population_trend": "Decreasing", "marine_system": false, "freshwater_system": true, "terrestrial_system": true, "assessor": "Dow, R.A.", "reviewer": "Clausnitzer, V.", "aoo_km2": "10-500", "eoo_km2": "56-1654,56-100", "elevation_upper": null, "elevation_lower": null, "depth_upper": null, "depth_lower": null, "errata_flag": null, "errata_reason": null, "amended_flag": null, "amended_reason": null}]}