{"id": "161326462", "result": [{"code": "2.1", "title": "Annual & perennial non-timber crops", "timing": "Future", "scope": null, "severity": null, "score": "No/Negligible Impact: 1", "invasive": null}, {"code": "2.1.1", "title": "Shifting agriculture", "timing": "Future", "scope": null, "severity": null, "score": "No/Negligible Impact: 1", "invasive": null}, {"code": "2.1.2", "title": "Small-holder farming", "timing": "Future", "scope": null, "severity": null, "score": "No/Negligible Impact: 1", "invasive": null}, {"code": "2.3", "title": "Livestock farming & ranching", "timing": "Future", "scope": null, "severity": null, "score": "No/Negligible Impact: 1", "invasive": null}, {"code": "2.3", "title": "Livestock farming & ranching", "timing": "Ongoing", "scope": null, "severity": null, "score": "Low Impact: 3", "invasive": null}, {"code": "2.3.1", "title": "Nomadic grazing", "timing": "Ongoing", "scope": null, "severity": null, "score": "Low Impact: 3", "invasive": null}, {"code": "2.3.2", "title": "Small-holder grazing, ranching or farming", "timing": "Future", "scope": null, "severity": null, "score": "No/Negligible Impact: 1", "invasive": null}, {"code": "3.2", "title": "Mining & quarrying", "timing": "Future", "scope": null, "severity": null, "score": "No/Negligible Impact: 1", "invasive": null}, {"code": "7.1", "title": "Fire & fire suppression", "timing": "Ongoing", "scope": null, "severity": null, "score": "Low Impact: 3", "invasive": null}, {"code": "7.1.1", "title": "Increase in fire frequency/intensity", "timing": "Ongoing", "scope": null, "severity": null, "score": "Low Impact: 3", "invasive": null}, {"code": "8.1", "title": "Invasive non-native/alien species/diseases (Acacia mearnsii)", "timing": "Ongoing", "scope": null, "severity": null, "score": "Low Impact: 3", "invasive": "Acacia mearnsii"}, {"code": "8.1.2", "title": "Named species (Acacia mearnsii)", "timing": "Ongoing", "scope": null, "severity": null, "score": "Low Impact: 3", "invasive": "Acacia mearnsii"}]}