{"name": "176164527", "result": [{"taxonid": 176164527, "scientific_name": "Cyphocharax biocellatus", "kingdom": "ANIMALIA", "phylum": "CHORDATA", "class": "ACTINOPTERYGII", "order": "CHARACIFORMES", "family": "CURIMATIDAE", "genus": "Cyphocharax", "main_common_name": "Cyphocharax Bi-ocell\u00e9", "authority": "Vari, Sidlauskas &amp; Le Bail, 2012", "published_year": 2023, "assessment_date": "2023-03-12", "category": "NT", "criteria": null, "population_trend": "Decreasing", "marine_system": false, "freshwater_system": true, "terrestrial_system": false, "assessor": "Lasso-Alcal\u00e1, O.M., Quintero-T., E., Mikolji, I. & Mart\u00ednez, E.O.", "reviewer": "Le Bail, P.-Y.", "aoo_km2": null, "eoo_km2": "15293-40235", "elevation_upper": null, "elevation_lower": null, "depth_upper": null, "depth_lower": null, "errata_flag": null, "errata_reason": null, "amended_flag": null, "amended_reason": null}]}