{"name": "176155201", "result": [{"taxonid": 176155201, "scientific_name": "Creagrutus planquettei", "kingdom": "ANIMALIA", "phylum": "CHORDATA", "class": "ACTINOPTERYGII", "order": "CHARACIFORMES", "family": "CHARACIDAE", "genus": "Creagrutus", "main_common_name": null, "authority": "G\u00e9ry &amp; Renno, 1989", "published_year": 2022, "assessment_date": "2020-12-14", "category": "VU", "criteria": "B1ab(iii)", "population_trend": "Stable", "marine_system": false, "freshwater_system": true, "terrestrial_system": false, "assessor": "Taphorn, D.C. & Rodr\u00edguez-Olarte, D.", "reviewer": "Villa-Navarro, F.", "aoo_km2": "36-6676,6676", "eoo_km2": "2225-8587,8587", "elevation_upper": 125, "elevation_lower": 5, "depth_upper": null, "depth_lower": null, "errata_flag": null, "errata_reason": null, "amended_flag": null, "amended_reason": null}]}