{"name": "187083", "result": [{"taxonid": 187083, "scientific_name": "Glandulocauda melanopleura", "kingdom": "ANIMALIA", "phylum": "CHORDATA", "class": "ACTINOPTERYGII", "order": "CHARACIFORMES", "family": "CHARACIDAE", "genus": "Glandulocauda", "main_common_name": null, "authority": "(Ellis, 1911)", "published_year": 2021, "assessment_date": "2020-10-29", "category": "EN", "criteria": "B1ab(iii,iv)", "population_trend": "Decreasing", "marine_system": false, "freshwater_system": true, "terrestrial_system": false, "assessor": "Lyons, T.J.", "reviewer": "Reis, R. & Carvalho, F.R.", "aoo_km2": null, "eoo_km2": "1790", "elevation_upper": null, "elevation_lower": null, "depth_upper": null, "depth_lower": null, "errata_flag": null, "errata_reason": null, "amended_flag": null, "amended_reason": null}]}