{"name": "176023661", "result": [{"taxonid": 176023661, "scientific_name": "Peckoltia lineola", "kingdom": "ANIMALIA", "phylum": "CHORDATA", "class": "ACTINOPTERYGII", "order": "SILURIFORMES", "family": "LORICARIIDAE", "genus": "Peckoltia", "main_common_name": null, "authority": "Armbruster, 2008", "published_year": 2023, "assessment_date": "2020-08-21", "category": "VU", "criteria": "B1ab(iii,v)+2ab(iii,v)", "population_trend": "Unknown", "marine_system": false, "freshwater_system": true, "terrestrial_system": false, "assessor": "Armbruster, J.W.", "reviewer": "Provenzano-Rizzi, F.", "aoo_km2": "1384", "eoo_km2": "6105", "elevation_upper": null, "elevation_lower": null, "depth_upper": null, "depth_lower": null, "errata_flag": null, "errata_reason": null, "amended_flag": null, "amended_reason": null}]}