{"id": "173831033", "result": [{"code": "2.1", "title": "Annual & perennial non-timber crops", "timing": "Ongoing", "scope": "Unknown", "severity": "Unknown", "score": "Unknown", "invasive": null}, {"code": "2.1.3", "title": "Agro-industry farming", "timing": "Ongoing", "scope": "Unknown", "severity": "Unknown", "score": "Unknown", "invasive": null}, {"code": "2.3", "title": "Livestock farming & ranching", "timing": "Ongoing", "scope": "Unknown", "severity": "Unknown", "score": "Unknown", "invasive": null}, {"code": "2.3.3", "title": "Agro-industry grazing, ranching or farming", "timing": "Ongoing", "scope": "Unknown", "severity": "Unknown", "score": "Unknown", "invasive": null}, {"code": "5.3", "title": "Logging & wood harvesting", "timing": "Ongoing", "scope": "Unknown", "severity": "Unknown", "score": "Unknown", "invasive": null}, {"code": "5.3.4", "title": "Unintentional effects: (large scale) [harvest]", "timing": "Ongoing", "scope": "Unknown", "severity": "Unknown", "score": "Unknown", "invasive": null}, {"code": "7.2", "title": "Dams & water management/use", "timing": "Ongoing", "scope": "Unknown", "severity": "Unknown", "score": "Unknown", "invasive": null}, {"code": "7.2.10", "title": "Large dams", "timing": "Ongoing", "scope": "Unknown", "severity": "Unknown", "score": "Unknown", "invasive": null}]}