{"name": "201528578", "result": [{"taxonid": 201528578, "scientific_name": "Koreozospeum nodongense", "kingdom": "ANIMALIA", "phylum": "MOLLUSCA", "class": "GASTROPODA", "order": "ELLOBIIDA", "family": "ELLOBIIDAE", "genus": "Koreozospeum", "main_common_name": null, "authority": "J.-S. Lee, Prozorova &amp; Jochum, 2015", "published_year": 2023, "assessment_date": "2023-03-20", "category": "EN", "criteria": "B1ab(iii,v)+2ab(iii,v)", "population_trend": "Increasing", "marine_system": false, "freshwater_system": false, "terrestrial_system": true, "assessor": "Chung, H.-Y.", "reviewer": "Westrip, J.R.S.", "aoo_km2": "4", "eoo_km2": "4", "elevation_upper": null, "elevation_lower": null, "depth_upper": null, "depth_lower": null, "errata_flag": null, "errata_reason": null, "amended_flag": null, "amended_reason": null}]}