{"id": "194868218", "result": [{"code": "2.1", "title": "Annual & perennial non-timber crops", "timing": "Ongoing", "scope": "Unknown", "severity": "Rapid Declines", "score": "Unknown", "invasive": null}, {"code": "2.1.4", "title": "Scale Unknown/Unrecorded", "timing": "Ongoing", "scope": "Unknown", "severity": "Rapid Declines", "score": "Unknown", "invasive": null}, {"code": "2.3", "title": "Livestock farming & ranching", "timing": "Ongoing", "scope": "Unknown", "severity": "Rapid Declines", "score": "Unknown", "invasive": null}, {"code": "2.3.4", "title": "Scale Unknown/Unrecorded", "timing": "Ongoing", "scope": "Unknown", "severity": "Rapid Declines", "score": "Unknown", "invasive": null}, {"code": "2.4", "title": "Marine & freshwater aquaculture", "timing": "Ongoing", "scope": "Unknown", "severity": "Rapid Declines", "score": "Unknown", "invasive": null}, {"code": "2.4.3", "title": "Scale Unknown/Unrecorded", "timing": "Ongoing", "scope": "Unknown", "severity": "Rapid Declines", "score": "Unknown", "invasive": null}]}